setup.cfg
setup.py
pytest_optional/__init__.py
pytest_optional/optional.py
pytest_optional/test_example1.py
pytest_optional.egg-info/PKG-INFO
pytest_optional.egg-info/SOURCES.txt
pytest_optional.egg-info/dependency_links.txt
pytest_optional.egg-info/requires.txt
pytest_optional.egg-info/top_level.txt