Metadata-Version: 1.1
Name: pytest-optional
Version: 0.0.2
Summary: include/exclude values of fixtures in pytest
Home-page: http://bitbucket.org/maho/pytest-optional
Author: Maho
Author-email: maho@pagema.net
License: UNKNOWN
Download-URL: https://bitbucket.org/maho/pytest-optional/get/0.0.2.tar.bz2
Keywords: pytest
Platform: UNKNOWN
